LICENSE
README.md
setup.py
py_smn.egg-info/PKG-INFO
py_smn.egg-info/SOURCES.txt
py_smn.egg-info/dependency_links.txt
py_smn.egg-info/requires.txt
py_smn.egg-info/top_level.txt
smn/__init__.py
smn/client.py
smn/constants.py
smn/exceptions.py
smn/forecast.py
smn/parser.py
smn/weather_station.py