Metadata-Version: 2.1
Name: py-smn
Version: 0.1.0
Summary: A Python wrapper for the SMN API Argentina
Home-page: https://github.com/manucabral/py-smn
Author: Manuel Cabral
License: MIT
Project-URL: Documentation, https://github.com/manucabral/py-smn/blob/main/README.md
Project-URL: Bug Tracker, https://github.com/manucabral/py-smn/issues
Keywords: smn,weather,forecast,api,argentina,smn-api
Classifier: Intended Audience :: Developers
Classifier: License :: OSI Approved :: MIT License
Classifier: Natural Language :: English
Classifier: Operating System :: OS Independent
Classifier: Programming Language :: Python :: 3
Classifier: Programming Language :: Python :: 3.10
Classifier: Programming Language :: Python :: 3.11
Requires-Python: >=3.6
License-File: LICENSE
